{
  "kind": "collectionType",
  "collectionName": "views",
  "info": {
    "name": "Views"
  },
  "options": {
    "increments": true,
    "timestamps": true,
    "draftAndPublish": true
  },
  "attributes": {
    "name": {
      "type": "string"
    },
    "source": {
      "type": "string"
    },
    "source_link": {
      "type": "string"
    },
    "lat": {
      "type": "float"
    },
    "lng": {
      "type": "float"
    },
    "image": {
      "model": "file",
      "via": "related",
      "allowedTypes": [
        "images",
        "files",
        "videos"
      ],
      "plugin": "upload",
      "required": false
    }
  }
}
